{
    "openapi": "3.0.0",
    "info": {
        "title": "Topvisor/Positions_2.Methods.Summary.Chart.Export.Get",
        "version": "2.0.0"
    },
    "paths": {},
    "components": {
        "schemas": {
            "Positions_2.Methods.Summary.Chart.Export.Get": {
                "type": "object",
                "properties": {
                    "reverse_dates": {
                        "title": "Использовать обратный порядок дат",
                        "type": "boolean"
                    },
                    "project_id": {
                        "$ref": "../../../../../TV/API/Params/ProjectIdTrait.json#/components/schemas/TV.API.Params.ProjectIdTrait/properties/project_id"
                    },
                    "region_index": {
                        "title": "Индекс региона",
                        "type": "integer"
                    },
                    "competitors_ids": {
                        "title": "ID конкурентов",
                        "nullable": true,
                        "allOf": [
                            {
                                "$ref": "../../../../../TV/API/Types/IntArray.json#/components/schemas/TV.API.Types.IntArray"
                            }
                        ]
                    },
                    "show_tops": {
                        "title": "Отобразить данные по топам",
                        "type": "boolean"
                    },
                    "show_avg": {
                        "title": "Отобразить среднюю позицию",
                        "type": "boolean"
                    },
                    "show_median": {
                        "title": "Отобразить медианную позицию",
                        "type": "boolean"
                    },
                    "show_visibility": {
                        "title": "Отобразить видимость",
                        "type": "boolean"
                    },
                    "group_folder_id_depth": {
                        "$ref": "../../../../../Keywords_2/Params/Keywords/ApiGetParams.json#/components/schemas/Keywords_2.Params.Keywords.ApiGetParams/properties/group_folder_id_depth"
                    },
                    "show_trash": {
                        "$ref": "../../../../../Keywords_2/Params/Keywords/ApiGetParams.json#/components/schemas/Keywords_2.Params.Keywords.ApiGetParams/properties/show_trash"
                    },
                    "only_exists_first_date": {
                        "allOf": [
                            {
                                "$ref": "../../../../../Reports_2/Types/OnlyExistsFirstDate.json#/components/schemas/Reports_2.Types.OnlyExistsFirstDate"
                            }
                        ]
                    },
                    "dates": {
                        "$ref": "../../../../../Reports_2/Params/DateRangeTrait.json#/components/schemas/Reports_2.Params.DateRangeTrait/properties/dates"
                    },
                    "type_range": {
                        "$ref": "../../../../../Reports_2/Params/DateRangeTrait.json#/components/schemas/Reports_2.Params.DateRangeTrait/properties/type_range"
                    },
                    "date1": {
                        "$ref": "../../../../../Reports_2/Params/DateRangeTrait.json#/components/schemas/Reports_2.Params.DateRangeTrait/properties/date1"
                    },
                    "date2": {
                        "$ref": "../../../../../Reports_2/Params/DateRangeTrait.json#/components/schemas/Reports_2.Params.DateRangeTrait/properties/date2"
                    },
                    "count_dates": {
                        "$ref": "../../../../../Reports_2/Params/DateRangeTrait.json#/components/schemas/Reports_2.Params.DateRangeTrait/properties/count_dates"
                    },
                    "period_days": {
                        "$ref": "../../../../../Reports_2/Params/DateRangeTrait.json#/components/schemas/Reports_2.Params.DateRangeTrait/properties/period_days"
                    },
                    "fields": {
                        "$ref": "../../../../../TV/API/Params/FieldsTrait.json#/components/schemas/TV.API.Params.FieldsTrait/properties/fields"
                    },
                    "orders": {
                        "$ref": "../../../../../TV/API/Params/OrdersTrait.json#/components/schemas/TV.API.Params.OrdersTrait/properties/orders"
                    },
                    "filters": {
                        "$ref": "../../../../../TV/API/Params/FiltersTrait.json#/components/schemas/TV.API.Params.FiltersTrait/properties/filters"
                    },
                    "id": {
                        "$ref": "../../../../../TV/API/Params/FiltersTrait.json#/components/schemas/TV.API.Params.FiltersTrait/properties/id"
                    },
                    "limit": {
                        "$ref": "../../../../../TV/API/Params/LimitTrait.json#/components/schemas/TV.API.Params.LimitTrait/properties/limit"
                    },
                    "offset": {
                        "$ref": "../../../../../TV/API/Params/OffsetTrait.json#/components/schemas/TV.API.Params.OffsetTrait/properties/offset"
                    }
                },
                "required": [
                    "project_id",
                    "region_index"
                ],
                "title": "Экспорт сводки с графика"
            },
            "Positions_2.Methods.Summary.Chart.Export.Get.Exec": {
                "type": "never"
            }
        }
    }
}