{
    "openapi": "3.0.0",
    "info": {
        "title": "Topvisor/Tpa_2.Methods.TestTpa.Get",
        "version": "2.0.0"
    },
    "paths": {},
    "components": {
        "schemas": {
            "Tpa_2.Methods.TestTpa.Get": {
                "type": "object",
                "properties": {
                    "provider": {
                        "allOf": [
                            {
                                "$ref": "../../../Tpa_2/Types/Provider.json#/components/schemas/Tpa_2.Types.Provider"
                            }
                        ]
                    },
                    "project_id": {
                        "$ref": "../../../TV/API/Params/ProjectIdTrait.json#/components/schemas/TV.API.Params.ProjectIdTrait/properties/project_id"
                    }
                },
                "required": [
                    "provider",
                    "project_id"
                ],
                "title": "@see jetbrains://idea/navigate/reference?project=topvisor.com&fqn=Services\\Tpa_2\\Methods\\TestTpa\\Get"
            },
            "Tpa_2.Methods.TestTpa.Get.Exec": {
                "type": "integer"
            }
        }
    }
}