{
    "openapi": "3.0.0",
    "info": {
        "title": "Topvisor/Payments_2.Methods.ValidateMerchantCardAP.Get",
        "version": "2.0.0"
    },
    "paths": {},
    "components": {
        "schemas": {
            "Payments_2.Methods.ValidateMerchantCardAP.Get": {
                "type": "object",
                "properties": {
                    "validation_url": {
                        "title": "URL для запроса к Apple Pay",
                        "type": "string"
                    }
                },
                "required": [
                    "validation_url"
                ],
                "title": "Валидация домена для подтверждения оплаты Apple Pay (system = card_ap)\n\n@see jetbrains://idea/navigate/reference?project=topvisor-com&fqn=Services\\Payments_2\\Methods\\ValidateMerchantCardAP\\Get"
            },
            "Payments_2.Methods.ValidateMerchantCardAP.Get.Exec": {
                "nullable": true,
                "type": "array"
            }
        }
    }
}