{
    "openapi": "3.0.0",
    "info": {
        "title": "Topvisor/Schedule_2.Types.Settings.Format",
        "version": "2.0.0"
    },
    "paths": {},
    "components": {
        "schemas": {
            "Schedule_2.Types.Settings.Format": {
                "type": "string",
                "enum": [
                    "csv",
                    "xlsx",
                    "pdf",
                    "html"
                ],
                "x-enum-varnames": [
                    "Csv",
                    "Xlsx",
                    "Pdf",
                    "Html"
                ],
                "x-enum-descriptions": [
                    null,
                    null,
                    null,
                    null
                ],
                "title": "Формат отчета\n\n@see jetbrains://idea/navigate/reference?project=topvisor-com&fqn=Services\\Schedule_2\\Types\\Settings\\Format"
            }
        }
    }
}