{
    "openapi": "3.0.0",
    "info": {
        "title": "Topvisor/Models.Apometr.History",
        "version": "2.0.0"
    },
    "paths": {},
    "components": {
        "schemas": {
            "Models.Apometr.History": {
                "properties": {
                    "time": {
                        "nullable": true
                    },
                    "action": {
                        "nullable": true
                    },
                    "region_index": {
                        "nullable": true
                    },
                    "keyword_id": {
                        "nullable": true
                    },
                    "url": {
                        "nullable": true
                    },
                    "position": {
                        "nullable": true
                    },
                    "d": {
                        "nullable": true
                    },
                    "d_day": {
                        "nullable": true
                    }
                }
            }
        }
    }
}