{
    "openapi": "3.0.0",
    "info": {
        "title": "Topvisor/Admin_2.Objects.Actions.Result",
        "version": "2.0.0"
    },
    "paths": {},
    "components": {
        "schemas": {
            "Admin_2.Objects.Actions.Result": {
                "type": "object",
                "properties": {
                    "isTest": {
                        "title": "Запущено ли дейсвтие в тестовом режиме",
                        "type": "boolean"
                    },
                    "info": {
                        "title": "Ассоциативный массив с информацией, связанной с выполняемым дейсвтием",
                        "type": "array",
                        "items": {
                            "type": "any"
                        }
                    },
                    "executionTime": {
                        "title": "Время выполнения дейсвтия",
                        "type": "number"
                    },
                    "memory": {
                        "title": "Информация о затраченных ресурсавах при выполнении дейсвтия",
                        "type": "array",
                        "items": {
                            "type": "any"
                        }
                    }
                },
                "required": [
                    "isTest",
                    "info",
                    "executionTime",
                    "memory"
                ],
                "title": "Результат выполнения действия"
            }
        }
    }
}